pySSV/__init__.py
pySSV/_frontend.py
pySSV/_version.py
pySSV/environment.py
pySSV/ssv_callback_dispatcher.py
pySSV/ssv_camera.py
pySSV/ssv_canvas.py
pySSV/ssv_canvas_stream_server.py
pySSV/ssv_colour.py
pySSV/ssv_fonts.py
pySSV/ssv_future.py
pySSV/ssv_gui.py
pySSV/ssv_logging.py
pySSV/ssv_pragma_parser.py
pySSV/ssv_render.py
pySSV/ssv_render_buffer.py
pySSV/ssv_render_opengl.py
pySSV/ssv_render_process_client.py
pySSV/ssv_render_process_server.py
pySSV/ssv_render_widget.py
pySSV/ssv_shader_args_tokenizer.py
pySSV/ssv_shader_preprocessor.py
pySSV/ssv_shader_source_preprocessor.py
pySSV/ssv_texture.py
pySSV/ssv_vertex_buffer.py
pySSV/fonts/NotoSans-SemiBold.fnt
pySSV/fonts/NotoSans-SemiBold.ttf
pySSV/fonts/OFL.txt
pySSV/fonts/__init__.py
pySSV/fonts/notosans.png
pySSV/shaders/__init__.py
pySSV/shaders/color_utils.glsl
pySSV/shaders/compat.glsl
pySSV/shaders/global_uniforms.glsl
pySSV/shaders/random.glsl
pySSV/shaders/sdf_ops.glsl
pySSV/shaders/template_full_screen_colour.glsl
pySSV/shaders/template_geometry.glsl
pySSV/shaders/template_pixel.glsl
pySSV/shaders/template_point_cloud.glsl
pySSV/shaders/template_render_test.glsl
pySSV/shaders/template_sdf.glsl
pySSV/shaders/template_shadertoy.glsl
pySSV/shaders/template_ui.glsl
pySSV/shaders/template_vert.glsl
pySSV/shaders/template_vert_pixel.glsl
pySSV/shaders/text.glsl
pySSV/tests/__init__.py
pySSV/tests/conftest.py
pySSV/tests/test_example.py
pySSV/tests/test_ssv_pragma_parser.py
pySSV/tests/test_ssv_preprocessor.py
pyssv-0.7.1.data/data/share/jupyter/labextensions/py-ssv/package.json
pyssv-0.7.1.data/data/share/jupyter/labextensions/py-ssv/static/312.33785fe162df7a224612.js
pyssv-0.7.1.data/data/share/jupyter/labextensions/py-ssv/static/480.06a86d0b88d9f42ace71.js
pyssv-0.7.1.data/data/share/jupyter/labextensions/py-ssv/static/568.9b3169ee39a42e4cc68f.js
pyssv-0.7.1.data/data/share/jupyter/labextensions/py-ssv/static/895.df74cd821b2218cf55b2.js
pyssv-0.7.1.dist-info/METADATA
pyssv-0.7.1.dist-info/WHEEL
pyssv-0.7.1.dist-info/licenses/LICENSE
pyssv-0.7.1.dist-info/RECORD
