Metadata-Version: 2.1
Name: pySSV
Version: 0.7.1
Summary: Leverage the power of shaders for scientific visualisation in Jupyter
Project-URL: Homepage, https://github.com/space928/Shaders-For-Scientific-Visualisation
Project-URL: Bug Tracker, https://github.com/space928/Shaders-For-Scientific-Visualisation/issues
Project-URL: Repository, https://github.com/space928/Shaders-For-Scientific-Visualisation.git
Author-email: Thomas Mathieson <thomas@mathieson.dev>
License: MIT License
License-File: LICENSE
Classifier: Environment :: GPU
Classifier: Framework :: Jupyter
Classifier: Framework :: Jupyter :: JupyterLab
Classifier: Framework :: Jupyter :: JupyterLab :: 4
Classifier: Framework :: Jupyter :: JupyterLab :: Extensions
Classifier: Framework :: Jupyter :: JupyterLab :: Extensions :: Prebuilt
Classifier: Intended Audience :: Developers
Classifier: Intended Audience :: Science/Research
Classifier: License :: OSI Approved :: MIT License
Classifier: Programming Language :: Python
Classifier: Programming Language :: Python :: 3
Classifier: Programming Language :: Python :: 3.8
Classifier: Programming Language :: Python :: 3.9
Classifier: Programming Language :: Python :: 3.10
Classifier: Programming Language :: Python :: 3.11
Classifier: Programming Language :: Python :: 3.12
Classifier: Topic :: Multimedia :: Graphics
Classifier: Topic :: Multimedia :: Graphics :: 3D Rendering
Classifier: Topic :: Multimedia :: Graphics :: Viewers
Classifier: Topic :: Scientific/Engineering :: Visualization
Classifier: Typing :: Typed
Requires-Python: >=3.8
Requires-Dist: av~=11.0.0
Requires-Dist: ipywidgets>=8.0.0
Requires-Dist: moderngl~=5.10.0
Requires-Dist: numpy>=1.22.0; python_version <= '3.10'
Requires-Dist: numpy>=1.24.0; python_version == '3.11'
Requires-Dist: numpy>=1.26.0; python_version == '3.12'
Requires-Dist: pcpp~=1.30
Requires-Dist: pillow~=10.1.0
Requires-Dist: portpicker~=1.6.0
Requires-Dist: types-pillow~=10.1.0
Requires-Dist: websockets~=12.0
Provides-Extra: docs
Requires-Dist: clang~=14.0.0; extra == 'docs'
Requires-Dist: jupyter-sphinx; extra == 'docs'
Requires-Dist: nbsphinx; extra == 'docs'
Requires-Dist: nbsphinx-link; extra == 'docs'
Requires-Dist: pypandoc; extra == 'docs'
Requires-Dist: pytest-check-links; extra == 'docs'
Requires-Dist: recommonmark; extra == 'docs'
Requires-Dist: sphinx-c-autodoc; extra == 'docs'
Requires-Dist: sphinx-rtd-theme; extra == 'docs'
Requires-Dist: sphinx>=1.5; extra == 'docs'
Provides-Extra: examples
Provides-Extra: test
Requires-Dist: nbval; extra == 'test'
Requires-Dist: pytest-cov; extra == 'test'
Requires-Dist: pytest>=6.0; extra == 'test'
